versein/__init__.py
versein/__main__.py
versein/_version.py
versein/greeting.py
versein-0.1.3.dist-info/LICENSE
versein-0.1.3.dist-info/METADATA
versein-0.1.3.dist-info/WHEEL
versein-0.1.3.dist-info/RECORD
