Metadata-Version: 2.3
Name: versein
Version: 0.1.3
Summary: Minimal Python SDK with Greeter class
License: MIT
Author: Muhammad Azeem
Author-email: you@example.com
Requires-Python: >=3.10,<4.0
Classifier: License :: OSI Approved :: MIT License
Classifier: Programming Language :: Python :: 3
Classifier: Programming Language :: Python :: 3.10
Classifier: Programming Language :: Python :: 3.11
Classifier: Programming Language :: Python :: 3.12
Classifier: Programming Language :: Python :: 3.13
